gpddatabase/DataObject.py
gpddatabase/DataObjectCorrelation.py
gpddatabase/DataObjectCorrelationMatrix.py
gpddatabase/DataObjectData.py
gpddatabase/DataObjectDataPoint.py
gpddatabase/DataObjectDataSet.py
gpddatabase/DataObjectGeneralInfo.py
gpddatabase/DataObjectKinematicBin.py
gpddatabase/DataObjectKinematics.py
gpddatabase/DataObjectObservable.py
gpddatabase/DataObjectReplicaSet.py
gpddatabase/DataObjectUUID.py
gpddatabase/DataObjectUncertainty.py
gpddatabase/DataObjectUncertaintySet.py
gpddatabase/DataTypes.py
gpddatabase/Exceptions.py
gpddatabase/ExclusiveDatabase.py
gpddatabase/GenericTypes.py
gpddatabase/MarkdownDataObject.py
gpddatabase/MarkdownDataObjectCorrelation.py
gpddatabase/MarkdownDataObjectCorrelationMatrix.py
gpddatabase/MarkdownDataObjectData.py
gpddatabase/MarkdownDataObjectDataPoint.py
gpddatabase/MarkdownDataObjectDataSet.py
gpddatabase/MarkdownDataObjectGeneralInfo.py
gpddatabase/MarkdownDataObjectKinematicBin.py
gpddatabase/MarkdownDataObjectKinematics.py
gpddatabase/MarkdownDataObjectObservable.py
gpddatabase/MarkdownDataObjectReplicaSet.py
gpddatabase/MarkdownDataObjectUUID.py
gpddatabase/MarkdownDataObjectUncertainty.py
gpddatabase/MarkdownDataObjectUncertaintySet.py
gpddatabase/MarkdownExclusiveDatabase.py
gpddatabase/ObservableTypes.py
gpddatabase/ParticleTypes.py
gpddatabase/RequiredTypes.py
gpddatabase/UnitGroupTypes.py
gpddatabase/UnitTypes.py
gpddatabase/VariableTypes.py
gpddatabase/__init__.py
gpddatabase/data/DVCS/CLAS_2001.yaml
gpddatabase/data/DVCS/CLAS_2006.yaml
gpddatabase/data/DVCS/CLAS_2007.yaml
gpddatabase/data/DVCS/CLAS_2009.yaml
gpddatabase/data/DVCS/CLAS_2015.yaml
gpddatabase/data/DVCS/CLAS_2015_2.yaml
gpddatabase/data/DVCS/CLAS_2018_1.yaml
gpddatabase/data/DVCS/CLAS_2018_2.yaml
gpddatabase/data/DVCS/CLAS_2023_1.yaml
gpddatabase/data/DVCS/CLAS_2023_2.yaml
gpddatabase/data/DVCS/COMPASS_2018.yaml
gpddatabase/data/DVCS/EPIC_2025.yaml
gpddatabase/data/DVCS/H1_2005_1.yaml
gpddatabase/data/DVCS/H1_2005_2.yaml
gpddatabase-1.1.3.dist-info/licenses/LICENSE
gpddatabase-1.1.3.dist-info/METADATA
gpddatabase-1.1.3.dist-info/WHEEL
gpddatabase-1.1.3.dist-info/top_level.txt
gpddatabase-1.1.3.dist-info/RECORD
