Metadata-Version: 2.4
Name: gpddatabase
Version: 1.1.3
Summary: Database for GPD physics
Project-URL: Homepage, https://github.com/opengpd/gpddatabase
Project-URL: Issues, https://github.com/opengpd/gpddatabase/issues
Classifier: Programming Language :: Python :: 3
Classifier: License :: OSI Approved :: GNU General Public License v3 (GPLv3)
Classifier: Operating System :: OS Independent
Classifier: Topic :: Scientific/Engineering :: Physics
Requires-Python: >=3.0
License-File: LICENSE
Requires-Dist: numpy
Requires-Dist: munch
Requires-Dist: particle
Requires-Dist: PyYAML
Dynamic: license-file
